finclaw/__init__.py
finclaw/__main__.py
finclaw/config.py
finclaw/data_store/__init__.py
finclaw/data_store/data_portal.py
finclaw/data_store/schema.py
finclaw/data_store/storage_clients/LocalStoreClient.py
finclaw/data_store/storage_clients/S3Client.py
finclaw/data_store/storage_clients/StoreClient.py
finclaw/data_store/storage_clients/__init__.py
finclaw/data_store/store.py
finclaw/data_store/storeV2.py
finclaw/data_store/validators.py
finclaw/utils/__init__.py
finclaw/utils/cli_utils.py
finclaw/utils/list_utils.py
finclaw/utils/progress_bar.py
finclaw/vendor/__init__.py
finclaw/vendor/constants/mic.py
finclaw/vendor/exceptions.py
finclaw/vendor/finnhub/__init__.py
finclaw/vendor/finnhub/finnhub_client.py
finclaw/vendor/finnhub/finnhub_to_table.py
finclaw/vendor/finnhub/models.py
finclaw/vendor/finnhub/pull_dividends.py
finclaw/vendor/finnhub/pull_financials.py
finclaw/vendor/finnhub/pull_insider_information.py
finclaw/vendor/finnhub/pull_ohcl.py
finclaw/vendor/finnhub/pull_ownership.py
finclaw/vendor/finnhub/pull_splits.py
finclaw/vendor/finnhub/symbols.py
finclaw/vendor/fmp/__init__.py
finclaw/vendor/fmp/fmp.py
finclaw/vendor/fmp/fmp_client.py
finclaw/vendor/fmp/models.py
finclaw/vendor/kraken/__init__.py
finclaw/vendor/kraken/exchange.py
finclaw/vendor/polygone/__init__.py
finclaw/vendor/twelvedata/__init__.py
finclaw/vendor/twelvedata/twelve.py
finclaw/vendor/twelvedata/twelve_client.py
finclaw-0.0.3.dist-info/METADATA
finclaw-0.0.3.dist-info/WHEEL
finclaw-0.0.3.dist-info/entry_points.txt
finclaw-0.0.3.dist-info/RECORD
