Metadata-Version: 2.1
Name: finclaw
Version: 0.0.3
Summary: 
Author: bobrinik
Author-email: bobrinik@pm.me
Requires-Python: >=3.10,<4.0
Classifier: Programming Language :: Python :: 3
Classifier: Programming Language :: Python :: 3.10
Classifier: Programming Language :: Python :: 3.11
Classifier: Programming Language :: Python :: 3.12
Requires-Dist: aiohttp (>=3.8.3,<4.0.0)
Requires-Dist: boto3 (>=1.34.24,<2.0.0)
Requires-Dist: click (>=8.1.3,<9.0.0)
Requires-Dist: google-cloud-storage (>=2.10.0,<3.0.0)
Requires-Dist: matplotlib (>=3.6.3,<4.0.0)
Requires-Dist: pandas (>=1.5.2,<2.0.0)
Requires-Dist: pyarrow (>=14.0.0,<15.0.0)
Requires-Dist: pydantic[dotenv] (>=1.10.4,<2.0.0)
Requires-Dist: requests (>=2.28.2,<3.0.0)
Requires-Dist: tqdm (>=4.64.1,<5.0.0)
